AUTHORS.txt
CHANGELOG.txt
FAQ.txt
INSTALL.txt
LICENSE.txt
MANIFEST.in
README.txt
THANKS.txt
TODO.txt
VERSION.txt
setup.py
doc/Makefile
doc/conf.py
doc/index.rst
pestotools/__init__.py
pestotools.genshi.egg-info/PKG-INFO
pestotools.genshi.egg-info/SOURCES.txt
pestotools.genshi.egg-info/dependency_links.txt
pestotools.genshi.egg-info/entry_points.txt
pestotools.genshi.egg-info/namespace_packages.txt
pestotools.genshi.egg-info/not-zip-safe
pestotools.genshi.egg-info/requires.txt
pestotools.genshi.egg-info/top_level.txt
pestotools/genshi/__init__.py