Metadata-Version: 1.0
Name: pestotools.genshi
Version: 0.2.3
Summary: Genshi integration tools for Pesto
Home-page: http://ollycope.com/software/pestotools.genshi/
Author: Oliver Cope
Author-email: oliver@redgecko.org
License: BSD
Platform: UNKNOWN
Classifier: Development Status :: 4 - Beta
Classifier: Environment :: Web Environment
Classifier: Intended Audience :: Developers
Classifier: License :: OSI Approved :: BSD License
Classifier: Operating System :: OS Independent
Classifier: Topic :: Internet :: WWW/HTTP :: WSGI
